swayipc/__init__.py
swayipc/criteria.py
swayipc/event.py
swayipc/ipc.py
swayipc/loadable.py
swayipc-0.1.2.dist-info/LICENSE
swayipc-0.1.2.dist-info/METADATA
swayipc-0.1.2.dist-info/WHEEL
swayipc-0.1.2.dist-info/top_level.txt
swayipc-0.1.2.dist-info/RECORD
