Metadata-Version: 2.1
Name: swayipc
Version: 0.1.2
Summary: Python bindings for communicating with the Sway window manager over its IPC socket.
Author: Evan Fosmark
License: MIT
Classifier: Development Status :: 3 - Alpha
Classifier: Programming Language :: Python :: 3
Classifier: License :: OSI Approved :: MIT License
Classifier: Intended Audience :: Developers
Classifier: Topic :: Desktop Environment :: Window Managers
Classifier: Typing :: Typed
Requires-Python: >=3.7
License-File: LICENSE
